<?xml version="1.0" encoding="UTF-8" standalone="no"?>
<compiereTrl baseLanguage="es_ES" language="es_ES" table="AD_MODULE" version="">
  <row id="CC49071E09CB4D8984365811C0D92F74" trl="N">
    <value column="Description" isTrl="N" original="Translation Spanish Production Custom Date">Translation Spanish Production Custom Date</value>
    <value column="Help" isTrl="N" original=""/>
    <value column="License" isTrl="N" original="Openbravo Public License">Openbravo Public License</value>
    <value column="Updateinfo" isTrl="N" original=""/>
  </row>
</compiereTrl>
