<?xml version="1.0"?>
  <database name="TABLE CRPCO_BUSINESSLINE">
    <table name="CRPCO_BUSINESSLINE" primaryKey="CRPCO_BLINE_PK_KEY">
      <column name="CRPCO_BUSINESSLINE_ID" primaryKey="true" required="true" type="VARCHAR" size="32" autoIncrement="false">
        <default/>
        <onCreateDefault/>
      </column>
      <column name="AD_CLIENT_ID" primaryKey="false" required="true" type="VARCHAR" size="32" autoIncrement="false">
        <default/>
        <onCreateDefault/>
      </column>
      <column name="AD_ORG_ID" primaryKey="false" required="true" type="VARCHAR" size="32" autoIncrement="false">
        <default/>
        <onCreateDefault/>
      </column>
      <column name="ISACTIVE" primaryKey="false" required="true" type="CHAR" size="1" autoIncrement="false">
        <default><![CDATA[Y]]></default>
        <onCreateDefault/>
      </column>
      <column name="CREATED" primaryKey="false" required="true" type="TIMESTAMP" size="7" autoIncrement="false">
        <default><![CDATA[SYSDATE]]></default>
        <onCreateDefault/>
      </column>
      <column name="CREATEDBY" primaryKey="false" required="true" type="VARCHAR" size="32" autoIncrement="false">
        <default/>
        <onCreateDefault/>
      </column>
      <column name="UPDATED" primaryKey="false" required="true" type="TIMESTAMP" size="7" autoIncrement="false">
        <default><![CDATA[SYSDATE]]></default>
        <onCreateDefault/>
      </column>
      <column name="UPDATEDBY" primaryKey="false" required="true" type="VARCHAR" size="32" autoIncrement="false">
        <default/>
        <onCreateDefault/>
      </column>
      <column name="BUSINESSLINENAME" primaryKey="false" required="true" type="VARCHAR" size="60" autoIncrement="false">
        <default/>
        <onCreateDefault/>
      </column>
      <foreign-key foreignTable="AD_CLIENT" name="CRPCO_BLINE_FK_CLIENT">
        <reference local="AD_CLIENT_ID" foreign="AD_CLIENT_ID"/>
      </foreign-key>
      <foreign-key foreignTable="AD_ORG" name="CRPCO_BLINE_FK_ORG">
        <reference local="AD_ORG_ID" foreign="AD_ORG_ID"/>
      </foreign-key>
      <unique name="CRPCO_UQ_BLINE">
        <unique-column name="BUSINESSLINENAME"/>
      </unique>
      <check name="CRPCO_BLINE_ISACTIVE_CHECK"><![CDATA[ISACTIVE IN ('Y', 'N')]]></check>
    </table>
  </database>
