<?xml version="1.0" encoding="UTF-8" standalone="no"?>
<compiereTrl baseLanguage="en_US" language="es_ES" table="AD_MENU" version="">
  <row id="2874BD36EBC244CEB1A71162B3C5D9A1" trl="Y">
    <value column="Name" isTrl="Y" original="Orders pending dispatch or billing">Pedidos pendientes de despacho o facturación</value>
    <value column="Description" isTrl="N" original="">Pedidos pendientes de despacho o facturación</value>
  </row>
  <row id="51058F951DEE4C93B985B014B9DB5E32" trl="Y">
    <value column="Name" isTrl="Y" original="Square Bills">Facturas Cuadradas</value>
    <value column="Description" isTrl="N" original=""/>
  </row>
  <row id="54DE921011384AD0830A9D56F1298D43" trl="Y">
    <value column="Name" isTrl="Y" original="Report Partial Sales Invoices without Dispatch">Reporte Facturas de Venta Parcial sin Despacho</value>
    <value column="Description" isTrl="Y" original="Report Partial Sales Invoices without Dispatch">Reporte Facturas de Venta Parcial sin Despacho</value>
  </row>
</compiereTrl>
