<?xml version="1.0" encoding="UTF-8" standalone="no"?>
<compiereTrl baseLanguage="en_US" language="es_ES" table="AD_TEXTINTERFACES" version="">
  <row id="02F6273AA6B84EDAA11E7D6D50DCBAE3" trl="N">
    <value column="Text" isTrl="N" original="NRO. LIQUIDACIÓN:">NRO. LIQUIDACIÓN:</value>
  </row>
  <row id="0F89FE41A7254047A77110C8F5DE8A46" trl="N">
    <value column="Text" isTrl="N" original="PAGO">PAGO</value>
  </row>
  <row id="144A61AF071141ED851328DC9C1FB489" trl="N">
    <value column="Text" isTrl="N" original="LIQUIDACIÓN DE PROYECTOS">LIQUIDACIÓN DE PROYECTOS</value>
  </row>
  <row id="16509DE610564963B52CB63A16BD7370" trl="N">
    <value column="Text" isTrl="N" original="producto">producto</value>
  </row>
  <row id="19A43D1540974D3CADA25891C2E58470" trl="N">
    <value column="Text" isTrl="N" original="Pagos y Anticipos">Pagos y Anticipos</value>
  </row>
  <row id="26B47BE651D84460B4AE7ED4997B79E9" trl="N">
    <value column="Text" isTrl="N" original="Facturas de Venta">Facturas de Venta</value>
  </row>
  <row id="2E52AFB1A437450AA7F5E3B5415F98C3" trl="N">
    <value column="Text" isTrl="N" original="REVISADO POR:">REVISADO POR:</value>
  </row>
  <row id="38B4BC5A2D2C4727BB36E8E130308409" trl="N">
    <value column="Text" isTrl="N" original="TOTALES">TOTALES</value>
  </row>
  <row id="3ED51F21719045D88EFAD264A962B090" trl="N">
    <value column="Text" isTrl="N" original="CANTIDAD">CANTIDAD</value>
  </row>
  <row id="476D18C36843458FB3739111AA278AA7" trl="N">
    <value column="Text" isTrl="N" original="PAGO">PAGO</value>
  </row>
  <row id="476EE153B4F4461193776498129DCE1C" trl="N">
    <value column="Text" isTrl="N" original="UNIDAD">UNIDAD</value>
  </row>
  <row id="553CACFEB92A4C89BF59BB772B663E5D" trl="N">
    <value column="Text" isTrl="N" original="CANTIDAD">CANTIDAD</value>
  </row>
  <row id="5736500F8AFF46CB8C554A386C24B3BD" trl="N">
    <value column="Text" isTrl="N" original="PROYECTO:">PROYECTO:</value>
  </row>
  <row id="5A1AD09F22114A53839C04A97C886E85" trl="N">
    <value column="Text" isTrl="N" original="VALOR">VALOR</value>
  </row>
  <row id="5B66DEDD656048E3871A73852663D8D5" trl="N">
    <value column="Text" isTrl="N" original="CODIGO">CODIGO</value>
  </row>
  <row id="5E537FC825A4435F9F7A1B2703F351CC" trl="N">
    <value column="Text" isTrl="N" original="FECHA">FECHA</value>
  </row>
  <row id="67103528B455489CB234BE51CA3BEFAD" trl="N">
    <value column="Text" isTrl="N" original="PRODUCTO">PRODUCTO</value>
  </row>
  <row id="6F61EDAC0A024552B85516652443BF56" trl="N">
    <value column="Text" isTrl="N" original="FECHA LIQUIDACIÓN:">FECHA LIQUIDACIÓN:</value>
  </row>
  <row id="78D9EBD45A2149A0800F642464D4FD42" trl="N">
    <value column="Text" isTrl="N" original="HABER">HABER</value>
  </row>
  <row id="8DC9B0787D1E437E9B6EEDEDE49922C0" trl="N">
    <value column="Text" isTrl="N" original="Costos Relacionados">Costos Relacionados</value>
  </row>
  <row id="8F0F0EA92A0E41E6B0EBC7BAC5987843" trl="N">
    <value column="Text" isTrl="N" original="VALOR">VALOR</value>
  </row>
  <row id="934DA140FB0D49C1A5418BD0E12D6DFB" trl="N">
    <value column="Text" isTrl="N" original="DESCRIPCION">DESCRIPCION</value>
  </row>
  <row id="9CF26ED4697042D3BD55C2DD946F4E27" trl="N">
    <value column="Text" isTrl="N" original="TIPO DE DOCUMENTO:">TIPO DE DOCUMENTO:</value>
  </row>
  <row id="9F6139C9FF084ED8AE29859A309EA397" trl="N">
    <value column="Text" isTrl="N" original="CUENTA">CUENTA</value>
  </row>
  <row id="A043CDABA2E8404EBF4F7F29186D05D2" trl="N">
    <value column="Text" isTrl="N" original="REPORTE CUADRE DE LIQUIDACIÓN DE PROYECTOS">REPORTE CUADRE DE LIQUIDACIÓN DE PROYECTOS</value>
  </row>
  <row id="A4B2A64F049E45918463EC0564C7D5C4" trl="N">
    <value column="Text" isTrl="N" original="DOCUMENTO">DOCUMENTO</value>
  </row>
  <row id="A506427313BB4D7DA798C3731E6BAA96" trl="N">
    <value column="Text" isTrl="N" original="TIPO DE LIQUIDACIÓN:">TIPO DE LIQUIDACIÓN:</value>
  </row>
  <row id="A63126ED540B48C0B3AFF1F616BBD9E0" trl="N">
    <value column="Text" isTrl="N" original="FECHA IMPRESION:">FECHA IMPRESION:</value>
  </row>
  <row id="A955ADB54E8D4C2F91EDF3422672649B" trl="N">
    <value column="Text" isTrl="N" original="COSTO">COSTO</value>
  </row>
  <row id="ABB6E619447944FD8DC6B1066BA4AA01" trl="N">
    <value column="Text" isTrl="N" original="PROYECTO">PROYECTO</value>
  </row>
  <row id="B4E3670546F04F78911E58149464FACA" trl="N">
    <value column="Text" isTrl="N" original="MATERIALES CONSUMIDOS EN PROYECTOS">MATERIALES CONSUMIDOS EN PROYECTOS</value>
  </row>
  <row id="B7A0F6A94027462C9DCB85E2B0090164" trl="N">
    <value column="Text" isTrl="N" original="PAGO">PAGO</value>
  </row>
  <row id="C49D1C49A6D04BBFA764AD9830EAEF55" trl="N">
    <value column="Text" isTrl="N" original="CODIGO">CODIGO</value>
  </row>
  <row id="C6A8E85546AC490AB918A6A9542EC86E" trl="N">
    <value column="Text" isTrl="N" original="UNIDAD">UNIDAD</value>
  </row>
  <row id="D0FC140FC4F94232B28FA680A8C70841" trl="N">
    <value column="Text" isTrl="N" original="PORYECTOS:">PORYECTOS:</value>
  </row>
  <row id="D2D58F4E45104C168D1F6D2B8A724134" trl="N">
    <value column="Text" isTrl="N" original="APROBADO POR:">APROBADO POR:</value>
  </row>
  <row id="E1B13300713F44E2B425135D45611705" trl="N">
    <value column="Text" isTrl="N" original="COSTO">COSTO</value>
  </row>
  <row id="E392A301E2894C5F8D3DB446B5ACD050" trl="N">
    <value column="Text" isTrl="N" original="DEBE">DEBE</value>
  </row>
  <row id="E3BAAC6C5B2D4880A5018A18D3ADEF5E" trl="N">
    <value column="Text" isTrl="N" original="FECHA">FECHA</value>
  </row>
  <row id="E95CCAFD67064A25BA608A79FEA439CB" trl="N">
    <value column="Text" isTrl="N" original="VALOR">VALOR</value>
  </row>
  <row id="EDE6BD1D3A36472E8BF986812E3D144E" trl="N">
    <value column="Text" isTrl="N" original="FECHA">FECHA</value>
  </row>
</compiereTrl>
