<?xml version="1.0" encoding="UTF-8" standalone="no"?>
<compiereTrl baseLanguage="en_US" language="es_ES" table="AD_MESSAGE" version="">
  <row id="3F9B82C3260C45AE828717458E640063" trl="Y">
    <value column="MsgText" isTrl="Y" original="The record cannot be deleted. It has records on the lines.">No se puede eliminar el registro. Tiene registros en las lineas</value>
    <value column="MsgTip" isTrl="N" original=""/>
  </row>
  <row id="C3E4D992D956464BAD49261F199B86D5" trl="Y">
    <value column="MsgText" isTrl="Y" original="Name can't be duplicated">Ya existe un registro con el mismo nombre</value>
    <value column="MsgTip" isTrl="N" original=""/>
  </row>
</compiereTrl>
