<?xml version="1.0" encoding="UTF-8" standalone="no"?>
<compiereTrl baseLanguage="en_US" language="es_ES" table="AD_ELEMENT" version="">
  <row id="029C8EC2A2974D539FA8752130E8D055" trl="N">
    <value column="Name" isTrl="N" original="Document type Inout">Document type Inout</value>
    <value column="PrintName" isTrl="N" original="Document type Inout">Document type Inout</value>
    <value column="Description" isTrl="N" original=""/>
    <value column="Help" isTrl="N" original=""/>
    <value column="PO_Description" isTrl="N" original=""/>
    <value column="PO_Help" isTrl="N" original=""/>
    <value column="PO_Name" isTrl="N" original=""/>
    <value column="PO_PrintName" isTrl="N" original=""/>
  </row>
  <row id="04D4C09AADF5437DA3FC088889FB8E1F" trl="N">
    <value column="Name" isTrl="Y" original="Total whithholding rent">Total Retención Renta</value>
    <value column="PrintName" isTrl="Y" original="Total whithholding rent">Total Retención Renta</value>
    <value column="Description" isTrl="N" original=""/>
    <value column="Help" isTrl="N" original=""/>
    <value column="PO_Description" isTrl="N" original=""/>
    <value column="PO_Help" isTrl="N" original=""/>
    <value column="PO_Name" isTrl="N" original=""/>
    <value column="PO_PrintName" isTrl="N" original=""/>
  </row>
  <row id="07CB9D4584CC4366811A55EADDC2009C" trl="N">
    <value column="Name" isTrl="Y" original="Amount rent line">Valor linea de retención</value>
    <value column="PrintName" isTrl="Y" original="Amount rent line">Valor linea de retención</value>
    <value column="Description" isTrl="N" original=""/>
    <value column="Help" isTrl="N" original=""/>
    <value column="PO_Description" isTrl="N" original=""/>
    <value column="PO_Help" isTrl="N" original=""/>
    <value column="PO_Name" isTrl="N" original=""/>
    <value column="PO_PrintName" isTrl="N" original=""/>
  </row>
  <row id="0FDB0EE031044B7A801F3656AE8359A3" trl="N">
    <value column="Name" isTrl="N" original="Campaign_ID">Campaign_ID</value>
    <value column="PrintName" isTrl="N" original="Campaign_ID">Campaign_ID</value>
    <value column="Description" isTrl="N" original=""/>
    <value column="Help" isTrl="N" original=""/>
    <value column="PO_Description" isTrl="N" original=""/>
    <value column="PO_Help" isTrl="N" original=""/>
    <value column="PO_Name" isTrl="N" original=""/>
    <value column="PO_PrintName" isTrl="N" original=""/>
  </row>
  <row id="13B91A1D1DC542E795A53F82812BD907" trl="N">
    <value column="Name" isTrl="N" original="EM_Imdlv_Load_Lines_Auth">EM_Imdlv_Load_Lines_Auth</value>
    <value column="PrintName" isTrl="N" original="EM_Imdlv_Load_Lines_Auth">EM_Imdlv_Load_Lines_Auth</value>
    <value column="Description" isTrl="N" original=""/>
    <value column="Help" isTrl="N" original=""/>
    <value column="PO_Description" isTrl="N" original=""/>
    <value column="PO_Help" isTrl="N" original=""/>
    <value column="PO_Name" isTrl="N" original=""/>
    <value column="PO_PrintName" isTrl="N" original=""/>
  </row>
  <row id="1C3D84C0D5854BC6B504E23AF70E2BBA" trl="N">
    <value column="Name" isTrl="Y" original="Date">Fecha</value>
    <value column="PrintName" isTrl="Y" original="Date">Fecha</value>
    <value column="Description" isTrl="N" original=""/>
    <value column="Help" isTrl="N" original=""/>
    <value column="PO_Description" isTrl="N" original=""/>
    <value column="PO_Help" isTrl="N" original=""/>
    <value column="PO_Name" isTrl="N" original=""/>
    <value column="PO_PrintName" isTrl="N" original=""/>
  </row>
  <row id="1C4A9BE3E543416CA4E0C657A17B3EE4" trl="N">
    <value column="Name" isTrl="Y" original="Amount line VAT">Valor linea IVA</value>
    <value column="PrintName" isTrl="Y" original="Amount line VAT">Valor linea IVA</value>
    <value column="Description" isTrl="N" original=""/>
    <value column="Help" isTrl="N" original=""/>
    <value column="PO_Description" isTrl="N" original=""/>
    <value column="PO_Help" isTrl="N" original=""/>
    <value column="PO_Name" isTrl="N" original=""/>
    <value column="PO_PrintName" isTrl="N" original=""/>
  </row>
  <row id="1E77426F42804B7E95FEDA3D7B1922BB" trl="N">
    <value column="Name" isTrl="N" original="Productvatxls">Productvatxls</value>
    <value column="PrintName" isTrl="N" original="Productvatxls">Productvatxls</value>
    <value column="Description" isTrl="N" original=""/>
    <value column="Help" isTrl="N" original=""/>
    <value column="PO_Description" isTrl="N" original=""/>
    <value column="PO_Help" isTrl="N" original=""/>
    <value column="PO_Name" isTrl="N" original=""/>
    <value column="PO_PrintName" isTrl="N" original=""/>
  </row>
  <row id="2362EC8A85C14B3EBDA96ABA29B51BF9" trl="N">
    <value column="Name" isTrl="Y" original="Product Default">Producto por defecto</value>
    <value column="PrintName" isTrl="Y" original="Product Default">Producto por defecto</value>
    <value column="Description" isTrl="N" original=""/>
    <value column="Help" isTrl="N" original=""/>
    <value column="PO_Description" isTrl="N" original=""/>
    <value column="PO_Help" isTrl="N" original=""/>
    <value column="PO_Name" isTrl="N" original=""/>
    <value column="PO_PrintName" isTrl="N" original=""/>
  </row>
  <row id="24A0AFF6FA694480B33DD669B9DDD522" trl="N">
    <value column="Name" isTrl="Y" original="Integrated Price">Precio Integrado</value>
    <value column="PrintName" isTrl="Y" original="Integrated Price">Precio Integrado</value>
    <value column="Description" isTrl="N" original=""/>
    <value column="Help" isTrl="N" original=""/>
    <value column="PO_Description" isTrl="N" original=""/>
    <value column="PO_Help" isTrl="N" original=""/>
    <value column="PO_Name" isTrl="N" original=""/>
    <value column="PO_PrintName" isTrl="N" original=""/>
  </row>
  <row id="2759A2AB392E4259AFF4D1248A5CDC7B" trl="N">
    <value column="Name" isTrl="Y" original="Language">Idioma</value>
    <value column="PrintName" isTrl="Y" original="Language">Idioma</value>
    <value column="Description" isTrl="N" original=""/>
    <value column="Help" isTrl="N" original=""/>
    <value column="PO_Description" isTrl="N" original=""/>
    <value column="PO_Help" isTrl="N" original=""/>
    <value column="PO_Name" isTrl="N" original=""/>
    <value column="PO_PrintName" isTrl="N" original=""/>
  </row>
  <row id="27ED2661264A41FB9E70D8810D9280C7" trl="N">
    <value column="Name" isTrl="Y" original="Code">Código</value>
    <value column="PrintName" isTrl="Y" original="Code">Código</value>
    <value column="Description" isTrl="N" original=""/>
    <value column="Help" isTrl="N" original=""/>
    <value column="PO_Description" isTrl="N" original=""/>
    <value column="PO_Help" isTrl="N" original=""/>
    <value column="PO_Name" isTrl="N" original=""/>
    <value column="PO_PrintName" isTrl="N" original=""/>
  </row>
  <row id="29FBFCDD12BC4A6098D498750AE74BC3" trl="N">
    <value column="Name" isTrl="Y" original="Withh. Renta">Retención Renta</value>
    <value column="PrintName" isTrl="Y" original="Withh. Renta">Retención Renta</value>
    <value column="Description" isTrl="N" original=""/>
    <value column="Help" isTrl="N" original=""/>
    <value column="PO_Description" isTrl="N" original=""/>
    <value column="PO_Help" isTrl="N" original=""/>
    <value column="PO_Name" isTrl="N" original=""/>
    <value column="PO_PrintName" isTrl="N" original=""/>
  </row>
  <row id="2CE301449BC54E02A6EDC6F4BCFDC7B2" trl="N">
    <value column="Name" isTrl="Y" original="Import Data Line">Lineas Importar datos</value>
    <value column="PrintName" isTrl="Y" original="Import Data Line">Lineas Importar datos</value>
    <value column="Description" isTrl="N" original=""/>
    <value column="Help" isTrl="N" original=""/>
    <value column="PO_Description" isTrl="N" original=""/>
    <value column="PO_Help" isTrl="N" original=""/>
    <value column="PO_Name" isTrl="N" original=""/>
    <value column="PO_PrintName" isTrl="N" original=""/>
  </row>
  <row id="2D5C46FE4E804405BC54ACD91311FA97" trl="N">
    <value column="Name" isTrl="Y" original="Receiver Identification">Identificación Receptor</value>
    <value column="PrintName" isTrl="Y" original="Receiver Identification">Identificación Receptor</value>
    <value column="Description" isTrl="N" original=""/>
    <value column="Help" isTrl="N" original=""/>
    <value column="PO_Description" isTrl="N" original=""/>
    <value column="PO_Help" isTrl="N" original=""/>
    <value column="PO_Name" isTrl="N" original=""/>
    <value column="PO_PrintName" isTrl="N" original=""/>
  </row>
  <row id="2E866FA3CEFB49F290AE7DD0A2E9AB0F" trl="N">
    <value column="Name" isTrl="Y" original="Voucher Data">Datos de Comprobantes</value>
    <value column="PrintName" isTrl="Y" original="Voucher Data">Datos de Comprobantes</value>
    <value column="Description" isTrl="N" original=""/>
    <value column="Help" isTrl="N" original=""/>
    <value column="PO_Description" isTrl="N" original=""/>
    <value column="PO_Help" isTrl="N" original=""/>
    <value column="PO_Name" isTrl="N" original=""/>
    <value column="PO_PrintName" isTrl="N" original=""/>
  </row>
  <row id="380FBDACB15246C48231BD55A66BEED5" trl="N">
    <value column="Name" isTrl="Y" original="Integrated Quantity">Cantidad Integrada</value>
    <value column="PrintName" isTrl="Y" original="Integrated Quantity">Cantidad Integrada</value>
    <value column="Description" isTrl="N" original=""/>
    <value column="Help" isTrl="N" original=""/>
    <value column="PO_Description" isTrl="N" original=""/>
    <value column="PO_Help" isTrl="N" original=""/>
    <value column="PO_Name" isTrl="N" original=""/>
    <value column="PO_PrintName" isTrl="N" original=""/>
  </row>
  <row id="387BB5B6602C499BBBC4A9BE25759447" trl="N">
    <value column="Name" isTrl="N" original="Voucher">Voucher</value>
    <value column="PrintName" isTrl="N" original="Voucher">Voucher</value>
    <value column="Description" isTrl="N" original=""/>
    <value column="Help" isTrl="N" original=""/>
    <value column="PO_Description" isTrl="N" original=""/>
    <value column="PO_Help" isTrl="N" original=""/>
    <value column="PO_Name" isTrl="N" original=""/>
    <value column="PO_PrintName" isTrl="N" original=""/>
  </row>
  <row id="3EA9A93299DB402C96C694B5896664BD" trl="N">
    <value column="Name" isTrl="Y" original="Link SRI">Enlace SRI</value>
    <value column="PrintName" isTrl="Y" original="Link SRI">Enlace SRI</value>
    <value column="Description" isTrl="N" original=""/>
    <value column="Help" isTrl="N" original=""/>
    <value column="PO_Description" isTrl="N" original=""/>
    <value column="PO_Help" isTrl="N" original=""/>
    <value column="PO_Name" isTrl="N" original=""/>
    <value column="PO_PrintName" isTrl="N" original=""/>
  </row>
  <row id="47BCF5694DEE4617AA1947F3868FD3DA" trl="N">
    <value column="Name" isTrl="N" original="Productrentxls">Productrentxls</value>
    <value column="PrintName" isTrl="N" original="Productrentxls">Productrentxls</value>
    <value column="Description" isTrl="N" original=""/>
    <value column="Help" isTrl="N" original=""/>
    <value column="PO_Description" isTrl="N" original=""/>
    <value column="PO_Help" isTrl="N" original=""/>
    <value column="PO_Name" isTrl="N" original=""/>
    <value column="PO_PrintName" isTrl="N" original=""/>
  </row>
  <row id="486025AB00C041FEBA5691ED6264C9FA" trl="N">
    <value column="Name" isTrl="Y" original="Doctype Withholding">Documento Retención</value>
    <value column="PrintName" isTrl="Y" original="Doctype Withholding">Documento Retención</value>
    <value column="Description" isTrl="N" original=""/>
    <value column="Help" isTrl="N" original=""/>
    <value column="PO_Description" isTrl="N" original=""/>
    <value column="PO_Help" isTrl="N" original=""/>
    <value column="PO_Name" isTrl="N" original=""/>
    <value column="PO_PrintName" isTrl="N" original=""/>
  </row>
  <row id="48CCD1AF546F4AAEBBAB86C834CABFE7" trl="N">
    <value column="Name" isTrl="Y" original="Authorization SRI">Authorización SRI</value>
    <value column="PrintName" isTrl="Y" original="Authorization SRI">Authorización SRI</value>
    <value column="Description" isTrl="N" original=""/>
    <value column="Help" isTrl="N" original=""/>
    <value column="PO_Description" isTrl="N" original=""/>
    <value column="PO_Help" isTrl="N" original=""/>
    <value column="PO_Name" isTrl="N" original=""/>
    <value column="PO_PrintName" isTrl="N" original=""/>
  </row>
  <row id="495FD49CA64842569B5F1C379519F4E2" trl="N">
    <value column="Name" isTrl="N" original="Total base imp vat">Total base imp vat</value>
    <value column="PrintName" isTrl="N" original="Total base imp vat">Total base imp vat</value>
    <value column="Description" isTrl="N" original=""/>
    <value column="Help" isTrl="N" original=""/>
    <value column="PO_Description" isTrl="N" original=""/>
    <value column="PO_Help" isTrl="N" original=""/>
    <value column="PO_Name" isTrl="N" original=""/>
    <value column="PO_PrintName" isTrl="N" original=""/>
  </row>
  <row id="50895C81C37E4D5E8A003843BAB778FE" trl="N">
    <value column="Name" isTrl="Y" original="Vouche Data Line">Linea Datos de comprobante</value>
    <value column="PrintName" isTrl="Y" original="Vouche Data Line">Linea Datos de comprobante</value>
    <value column="Description" isTrl="N" original=""/>
    <value column="Help" isTrl="N" original=""/>
    <value column="PO_Description" isTrl="N" original=""/>
    <value column="PO_Help" isTrl="N" original=""/>
    <value column="PO_Name" isTrl="N" original=""/>
    <value column="PO_PrintName" isTrl="N" original=""/>
  </row>
  <row id="526EC53C22904CAC958F8F805F1B4908" trl="N">
    <value column="Name" isTrl="Y" original="Import Data">Importar Datos</value>
    <value column="PrintName" isTrl="Y" original="Import Data">Importar Datos</value>
    <value column="Description" isTrl="N" original=""/>
    <value column="Help" isTrl="N" original=""/>
    <value column="PO_Description" isTrl="N" original=""/>
    <value column="PO_Help" isTrl="N" original=""/>
    <value column="PO_Name" isTrl="N" original=""/>
    <value column="PO_PrintName" isTrl="N" original=""/>
  </row>
  <row id="528523EB0ADC4C2DA825778D4E8EF573" trl="N">
    <value column="Name" isTrl="Y" original="Create Order">Crear Orden</value>
    <value column="PrintName" isTrl="Y" original="Create Order">Crear Orden</value>
    <value column="Description" isTrl="N" original=""/>
    <value column="Help" isTrl="N" original=""/>
    <value column="PO_Description" isTrl="N" original=""/>
    <value column="PO_Help" isTrl="N" original=""/>
    <value column="PO_Name" isTrl="N" original=""/>
    <value column="PO_PrintName" isTrl="N" original=""/>
  </row>
  <row id="56A73346DCBA4C94AB60A2B625198F9A" trl="N">
    <value column="Name" isTrl="Y" original="Create Invoice">Crear Facturas</value>
    <value column="PrintName" isTrl="Y" original="Create Invoice">Crear Facturas</value>
    <value column="Description" isTrl="N" original=""/>
    <value column="Help" isTrl="N" original=""/>
    <value column="PO_Description" isTrl="N" original=""/>
    <value column="PO_Help" isTrl="N" original=""/>
    <value column="PO_Name" isTrl="N" original=""/>
    <value column="PO_PrintName" isTrl="N" original=""/>
  </row>
  <row id="5C1C4C7F84394EAB83BA4F10765D3FE0" trl="N">
    <value column="Name" isTrl="Y" original="Createtrx2">Crear Transacciones</value>
    <value column="PrintName" isTrl="Y" original="Createtrx2">Crear Transacciones</value>
    <value column="Description" isTrl="N" original=""/>
    <value column="Help" isTrl="N" original=""/>
    <value column="PO_Description" isTrl="N" original=""/>
    <value column="PO_Help" isTrl="N" original=""/>
    <value column="PO_Name" isTrl="N" original=""/>
    <value column="PO_PrintName" isTrl="N" original=""/>
  </row>
  <row id="5DDF1DBEB722469FB22EABB640602D93" trl="N">
    <value column="Name" isTrl="Y" original="Code Tax">Código Impuesto</value>
    <value column="PrintName" isTrl="Y" original="Code Tax">Código Impuesto</value>
    <value column="Description" isTrl="N" original=""/>
    <value column="Help" isTrl="N" original=""/>
    <value column="PO_Description" isTrl="N" original=""/>
    <value column="PO_Help" isTrl="N" original=""/>
    <value column="PO_Name" isTrl="N" original=""/>
    <value column="PO_PrintName" isTrl="N" original=""/>
  </row>
  <row id="5EC71983916A4D6D9FA02C758B58DD4F" trl="N">
    <value column="Name" isTrl="Y" original="Year">Año</value>
    <value column="PrintName" isTrl="Y" original="Year">Año</value>
    <value column="Description" isTrl="N" original=""/>
    <value column="Help" isTrl="N" original=""/>
    <value column="PO_Description" isTrl="N" original=""/>
    <value column="PO_Help" isTrl="N" original=""/>
    <value column="PO_Name" isTrl="N" original=""/>
    <value column="PO_PrintName" isTrl="N" original=""/>
  </row>
  <row id="615ED674604B423D9EA07EDC3794ED41" trl="N">
    <value column="Name" isTrl="Y" original="Discount">Descuento</value>
    <value column="PrintName" isTrl="Y" original="Discount">Descuento</value>
    <value column="Description" isTrl="N" original=""/>
    <value column="Help" isTrl="N" original=""/>
    <value column="PO_Description" isTrl="N" original=""/>
    <value column="PO_Help" isTrl="N" original=""/>
    <value column="PO_Name" isTrl="N" original=""/>
    <value column="PO_PrintName" isTrl="N" original=""/>
  </row>
  <row id="6248F4FDBEF54EDFA37688035BF6DAC9" trl="N">
    <value column="Name" isTrl="N" original="Total base imp">Total base imp</value>
    <value column="PrintName" isTrl="N" original="Total base imp">Total base imp</value>
    <value column="Description" isTrl="N" original=""/>
    <value column="Help" isTrl="N" original=""/>
    <value column="PO_Description" isTrl="N" original=""/>
    <value column="PO_Help" isTrl="N" original=""/>
    <value column="PO_Name" isTrl="N" original=""/>
    <value column="PO_PrintName" isTrl="N" original=""/>
  </row>
  <row id="64AC5BDC625646B390BBA1B3451B25F4" trl="N">
    <value column="Name" isTrl="Y" original="Duedate">Fecha de venciemiento</value>
    <value column="PrintName" isTrl="Y" original="Duedate">Fecha de venciemiento</value>
    <value column="Description" isTrl="N" original=""/>
    <value column="Help" isTrl="N" original=""/>
    <value column="PO_Description" isTrl="N" original=""/>
    <value column="PO_Help" isTrl="N" original=""/>
    <value column="PO_Name" isTrl="N" original=""/>
    <value column="PO_PrintName" isTrl="N" original=""/>
  </row>
  <row id="6D2EF111F45749BD86C6D8DF0963D268" trl="N">
    <value column="Name" isTrl="Y" original="Status Email">Estado correo</value>
    <value column="PrintName" isTrl="Y" original="Status Email">Estado correo</value>
    <value column="Description" isTrl="N" original=""/>
    <value column="Help" isTrl="N" original=""/>
    <value column="PO_Description" isTrl="N" original=""/>
    <value column="PO_Help" isTrl="N" original=""/>
    <value column="PO_Name" isTrl="N" original=""/>
    <value column="PO_PrintName" isTrl="N" original=""/>
  </row>
  <row id="6D6E4D26EDA34920BAE6A78A00B799C8" trl="N">
    <value column="Name" isTrl="N" original="Importtype">Importtype</value>
    <value column="PrintName" isTrl="N" original="Importtype">Importtype</value>
    <value column="Description" isTrl="N" original=""/>
    <value column="Help" isTrl="N" original=""/>
    <value column="PO_Description" isTrl="N" original=""/>
    <value column="PO_Help" isTrl="N" original=""/>
    <value column="PO_Name" isTrl="N" original=""/>
    <value column="PO_PrintName" isTrl="N" original=""/>
  </row>
  <row id="71841529A5B446BA9B9743DD1A7EED9D" trl="N">
    <value column="Name" isTrl="Y" original="Vat">IVA</value>
    <value column="PrintName" isTrl="Y" original="Vat">IVA</value>
    <value column="Description" isTrl="N" original=""/>
    <value column="Help" isTrl="N" original=""/>
    <value column="PO_Description" isTrl="N" original=""/>
    <value column="PO_Help" isTrl="N" original=""/>
    <value column="PO_Name" isTrl="N" original=""/>
    <value column="PO_PrintName" isTrl="N" original=""/>
  </row>
  <row id="726DE4400D7C4E10A870A47E8B7A8FBB" trl="N">
    <value column="Name" isTrl="Y" original="Total withholding source">Total retención renta</value>
    <value column="PrintName" isTrl="Y" original="Total withholding source">Total retención renta</value>
    <value column="Description" isTrl="N" original=""/>
    <value column="Help" isTrl="N" original=""/>
    <value column="PO_Description" isTrl="N" original=""/>
    <value column="PO_Help" isTrl="N" original=""/>
    <value column="PO_Name" isTrl="N" original=""/>
    <value column="PO_PrintName" isTrl="N" original=""/>
  </row>
  <row id="737A33C6F16346ACB9BC9558EE8E7F53" trl="N">
    <value column="Name" isTrl="Y" original="Authorization Purchase Load">Cargar Autorización Compras</value>
    <value column="PrintName" isTrl="Y" original="Authorization Purchase Load">Cargar Autorización Compras</value>
    <value column="Description" isTrl="N" original=""/>
    <value column="Help" isTrl="N" original=""/>
    <value column="PO_Description" isTrl="N" original=""/>
    <value column="PO_Help" isTrl="N" original=""/>
    <value column="PO_Name" isTrl="N" original=""/>
    <value column="PO_PrintName" isTrl="N" original=""/>
  </row>
  <row id="73BB553395A14D93B0B6187DF655CB0B" trl="N">
    <value column="Name" isTrl="Y" original="Date Payment">Fecha Pago</value>
    <value column="PrintName" isTrl="Y" original="Date Payment">Fecha Pago</value>
    <value column="Description" isTrl="N" original=""/>
    <value column="Help" isTrl="N" original=""/>
    <value column="PO_Description" isTrl="N" original=""/>
    <value column="PO_Help" isTrl="N" original=""/>
    <value column="PO_Name" isTrl="N" original=""/>
    <value column="PO_PrintName" isTrl="N" original=""/>
  </row>
  <row id="73DFC33122A74D339E3D1A98C5A2F7A1" trl="N">
    <value column="Name" isTrl="Y" original="Taxpayer">Tipo de contribuyente</value>
    <value column="PrintName" isTrl="Y" original="Taxpayer">Tipo de contribuyente</value>
    <value column="Description" isTrl="N" original=""/>
    <value column="Help" isTrl="N" original=""/>
    <value column="PO_Description" isTrl="N" original=""/>
    <value column="PO_Help" isTrl="N" original=""/>
    <value column="PO_Name" isTrl="N" original=""/>
    <value column="PO_PrintName" isTrl="N" original=""/>
  </row>
  <row id="745FCCFBE4014A0FBCF6A662AE41C24E" trl="N">
    <value column="Name" isTrl="Y" original="Reference payment">Referencia pago</value>
    <value column="PrintName" isTrl="Y" original="Reference payment">Referencia pago</value>
    <value column="Description" isTrl="N" original=""/>
    <value column="Help" isTrl="N" original=""/>
    <value column="PO_Description" isTrl="N" original=""/>
    <value column="PO_Help" isTrl="N" original=""/>
    <value column="PO_Name" isTrl="N" original=""/>
    <value column="PO_PrintName" isTrl="N" original=""/>
  </row>
  <row id="764A4B6FD6BC4649A8BAD889C9314AAC" trl="N">
    <value column="Name" isTrl="Y" original="User">Usuario</value>
    <value column="PrintName" isTrl="Y" original="User">Usuario</value>
    <value column="Description" isTrl="N" original=""/>
    <value column="Help" isTrl="N" original=""/>
    <value column="PO_Description" isTrl="N" original=""/>
    <value column="PO_Help" isTrl="N" original=""/>
    <value column="PO_Name" isTrl="N" original=""/>
    <value column="PO_PrintName" isTrl="N" original=""/>
  </row>
  <row id="79AB576230AC48CDB53C5970F442DE9B" trl="N">
    <value column="Name" isTrl="N" original="Formato">Formato</value>
    <value column="PrintName" isTrl="N" original="Formato">Formato</value>
    <value column="Description" isTrl="N" original=""/>
    <value column="Help" isTrl="N" original=""/>
    <value column="PO_Description" isTrl="N" original=""/>
    <value column="PO_Help" isTrl="N" original=""/>
    <value column="PO_Name" isTrl="N" original=""/>
    <value column="PO_PrintName" isTrl="N" original=""/>
  </row>
  <row id="7B1EFCACE3204BCDAA7B462A69D5F9E9" trl="N">
    <value column="Name" isTrl="Y" original="Lot">Lote</value>
    <value column="PrintName" isTrl="Y" original="Lot">Lote</value>
    <value column="Description" isTrl="N" original=""/>
    <value column="Help" isTrl="N" original=""/>
    <value column="PO_Description" isTrl="N" original=""/>
    <value column="PO_Help" isTrl="N" original=""/>
    <value column="PO_Name" isTrl="N" original=""/>
    <value column="PO_PrintName" isTrl="N" original=""/>
  </row>
  <row id="7B58632F45F14E268FDFECA8FC4C8F6F" trl="N">
    <value column="Name" isTrl="Y" original="Total withholding vat">Total retención IVA</value>
    <value column="PrintName" isTrl="Y" original="Total withholding vat">Total retención IVA</value>
    <value column="Description" isTrl="N" original=""/>
    <value column="Help" isTrl="N" original=""/>
    <value column="PO_Description" isTrl="N" original=""/>
    <value column="PO_Help" isTrl="N" original=""/>
    <value column="PO_Name" isTrl="N" original=""/>
    <value column="PO_PrintName" isTrl="N" original=""/>
  </row>
  <row id="7F268484325241478B3B49AFD88BC1DE" trl="N">
    <value column="Name" isTrl="N" original="Initialunitprice">Initialunitprice</value>
    <value column="PrintName" isTrl="N" original="Initialunitprice">Initialunitprice</value>
    <value column="Description" isTrl="N" original=""/>
    <value column="Help" isTrl="N" original=""/>
    <value column="PO_Description" isTrl="N" original=""/>
    <value column="PO_Help" isTrl="N" original=""/>
    <value column="PO_Name" isTrl="N" original=""/>
    <value column="PO_PrintName" isTrl="N" original=""/>
  </row>
  <row id="7F59A591430F4FF2A0FA82768A537B7E" trl="N">
    <value column="Name" isTrl="Y" original="Total Invoice">Total Factura</value>
    <value column="PrintName" isTrl="Y" original="Total Invoice">Total Factura</value>
    <value column="Description" isTrl="N" original=""/>
    <value column="Help" isTrl="N" original=""/>
    <value column="PO_Description" isTrl="N" original=""/>
    <value column="PO_Help" isTrl="N" original=""/>
    <value column="PO_Name" isTrl="N" original=""/>
    <value column="PO_PrintName" isTrl="N" original=""/>
  </row>
  <row id="80DF2F7424424DCE9043C1B25E78CAD8" trl="N">
    <value column="Name" isTrl="Y" original="Document Type">Tipo de Documento</value>
    <value column="PrintName" isTrl="Y" original="Document Type">Tipo de Documento</value>
    <value column="Description" isTrl="N" original=""/>
    <value column="Help" isTrl="N" original=""/>
    <value column="PO_Description" isTrl="N" original=""/>
    <value column="PO_Help" isTrl="N" original=""/>
    <value column="PO_Name" isTrl="N" original=""/>
    <value column="PO_PrintName" isTrl="N" original=""/>
  </row>
  <row id="834571EE2D5E43F695C0BED0C2DE0F93" trl="N">
    <value column="Name" isTrl="Y" original="Address">Dirección</value>
    <value column="PrintName" isTrl="Y" original="Address">Dirección</value>
    <value column="Description" isTrl="N" original=""/>
    <value column="Help" isTrl="N" original=""/>
    <value column="PO_Description" isTrl="N" original=""/>
    <value column="PO_Help" isTrl="N" original=""/>
    <value column="PO_Name" isTrl="N" original=""/>
    <value column="PO_PrintName" isTrl="N" original=""/>
  </row>
  <row id="86DDD5630A59471AAE582DBCE64E8F93" trl="N">
    <value column="Name" isTrl="Y" original="Proccess Data">Procesar Datos</value>
    <value column="PrintName" isTrl="Y" original="Proccess Data">Procesar Datos</value>
    <value column="Description" isTrl="N" original=""/>
    <value column="Help" isTrl="N" original=""/>
    <value column="PO_Description" isTrl="N" original=""/>
    <value column="PO_Help" isTrl="N" original=""/>
    <value column="PO_Name" isTrl="N" original=""/>
    <value column="PO_PrintName" isTrl="N" original=""/>
  </row>
  <row id="8C2C7FB7413F410182FBAB655730637D" trl="N">
    <value column="Name" isTrl="Y" original="Integrated Net price">Precio Neto integrado</value>
    <value column="PrintName" isTrl="Y" original="Integrated Net price">Precio Neto integrado</value>
    <value column="Description" isTrl="N" original=""/>
    <value column="Help" isTrl="N" original=""/>
    <value column="PO_Description" isTrl="N" original=""/>
    <value column="PO_Help" isTrl="N" original=""/>
    <value column="PO_Name" isTrl="N" original=""/>
    <value column="PO_PrintName" isTrl="N" original=""/>
  </row>
  <row id="8DB2A582096B4C588CF6C13638657BBE" trl="N">
    <value column="Name" isTrl="Y" original="Data Load">Cargar Datos</value>
    <value column="PrintName" isTrl="Y" original="Data Load">Cargar Datos</value>
    <value column="Description" isTrl="N" original=""/>
    <value column="Help" isTrl="N" original=""/>
    <value column="PO_Description" isTrl="N" original=""/>
    <value column="PO_Help" isTrl="N" original=""/>
    <value column="PO_Name" isTrl="N" original=""/>
    <value column="PO_PrintName" isTrl="N" original=""/>
  </row>
  <row id="8DB572880C1F413A96A82DA745211CD1" trl="N">
    <value column="Name" isTrl="Y" original="Description">Descripción</value>
    <value column="PrintName" isTrl="Y" original="Description">Descripción</value>
    <value column="Description" isTrl="N" original=""/>
    <value column="Help" isTrl="N" original=""/>
    <value column="PO_Description" isTrl="N" original=""/>
    <value column="PO_Help" isTrl="N" original=""/>
    <value column="PO_Name" isTrl="N" original=""/>
    <value column="PO_PrintName" isTrl="N" original=""/>
  </row>
  <row id="8EED7A1BA72E42DE86347465CBC6F0A7" trl="N">
    <value column="Name" isTrl="N" original="Refundedinvline_Ref_ID">Refundedinvline_Ref_ID</value>
    <value column="PrintName" isTrl="N" original="Refundedinvline_Ref_ID">Refundedinvline_Ref_ID</value>
    <value column="Description" isTrl="N" original=""/>
    <value column="Help" isTrl="N" original=""/>
    <value column="PO_Description" isTrl="N" original=""/>
    <value column="PO_Help" isTrl="N" original=""/>
    <value column="PO_Name" isTrl="N" original=""/>
    <value column="PO_PrintName" isTrl="N" original=""/>
  </row>
  <row id="8F95E1E93EC24F379542BEC3B0A7406B" trl="N">
    <value column="Name" isTrl="Y" original="Codelivelihoodt">Código de sustento</value>
    <value column="PrintName" isTrl="Y" original="Codelivelihoodt">Código de sustento</value>
    <value column="Description" isTrl="N" original=""/>
    <value column="Help" isTrl="N" original=""/>
    <value column="PO_Description" isTrl="N" original=""/>
    <value column="PO_Help" isTrl="N" original=""/>
    <value column="PO_Name" isTrl="N" original=""/>
    <value column="PO_PrintName" isTrl="N" original=""/>
  </row>
  <row id="90D23245ACF142ACB404ED4FFBCA5815" trl="N">
    <value column="Name" isTrl="Y" original="Subtotal not oject vat">Subtotal no objeto de IVA</value>
    <value column="PrintName" isTrl="Y" original="Subtotal not oject vat">Subtotal no objeto de IVA</value>
    <value column="Description" isTrl="N" original=""/>
    <value column="Help" isTrl="N" original=""/>
    <value column="PO_Description" isTrl="N" original=""/>
    <value column="PO_Help" isTrl="N" original=""/>
    <value column="PO_Name" isTrl="N" original=""/>
    <value column="PO_PrintName" isTrl="N" original=""/>
  </row>
  <row id="922CF2F7365840EA89653C869949FED9" trl="N">
    <value column="Name" isTrl="Y" original="Authorization No.">Nro, Autorización</value>
    <value column="PrintName" isTrl="Y" original="Authorization No.">Nro, Autorización</value>
    <value column="Description" isTrl="N" original=""/>
    <value column="Help" isTrl="N" original=""/>
    <value column="PO_Description" isTrl="N" original=""/>
    <value column="PO_Help" isTrl="N" original=""/>
    <value column="PO_Name" isTrl="N" original=""/>
    <value column="PO_PrintName" isTrl="N" original=""/>
  </row>
  <row id="92EB74888B4C442CA5E161A1A97119C2" trl="N">
    <value column="Name" isTrl="Y" original="Integrated Total amount">Total monto integrado</value>
    <value column="PrintName" isTrl="Y" original="Integrated Total amount">Total monto integrado</value>
    <value column="Description" isTrl="N" original=""/>
    <value column="Help" isTrl="N" original=""/>
    <value column="PO_Description" isTrl="N" original=""/>
    <value column="PO_Help" isTrl="N" original=""/>
    <value column="PO_Name" isTrl="N" original=""/>
    <value column="PO_PrintName" isTrl="N" original=""/>
  </row>
  <row id="935CC29BF892468A954117F7A1E76B93" trl="N">
    <value column="Name" isTrl="N" original="Xml_SRI">Xml_SRI</value>
    <value column="PrintName" isTrl="N" original="Xml_SRI">Xml_SRI</value>
    <value column="Description" isTrl="N" original=""/>
    <value column="Help" isTrl="N" original=""/>
    <value column="PO_Description" isTrl="N" original=""/>
    <value column="PO_Help" isTrl="N" original=""/>
    <value column="PO_Name" isTrl="N" original=""/>
    <value column="PO_PrintName" isTrl="N" original=""/>
  </row>
  <row id="952AD78FAA8C4FD5BF944F9FA2AB25C7" trl="N">
    <value column="Name" isTrl="Y" original="Document type withholdings source">Tipo de documento para comprobantes de retención</value>
    <value column="PrintName" isTrl="Y" original="Document type withholdings source">Tipo de documento para comprobantes de retención</value>
    <value column="Description" isTrl="N" original=""/>
    <value column="Help" isTrl="N" original=""/>
    <value column="PO_Description" isTrl="N" original=""/>
    <value column="PO_Help" isTrl="N" original=""/>
    <value column="PO_Name" isTrl="N" original=""/>
    <value column="PO_PrintName" isTrl="N" original=""/>
  </row>
  <row id="9CE59F503B264D529F0F4BCC99018C8F" trl="N">
    <value column="Name" isTrl="Y" original="Tax">Impuestos</value>
    <value column="PrintName" isTrl="N" original="Tax">Tax</value>
    <value column="Description" isTrl="N" original=""/>
    <value column="Help" isTrl="N" original=""/>
    <value column="PO_Description" isTrl="N" original=""/>
    <value column="PO_Help" isTrl="N" original=""/>
    <value column="PO_Name" isTrl="N" original=""/>
    <value column="PO_PrintName" isTrl="N" original=""/>
  </row>
  <row id="A05A295B79914FBFAF5C343E11C54E9B" trl="N">
    <value column="Name" isTrl="N" original="Initial_Subtotal1">Initial_Subtotal1</value>
    <value column="PrintName" isTrl="N" original="Initial_Subtotal1">Initial_Subtotal1</value>
    <value column="Description" isTrl="N" original=""/>
    <value column="Help" isTrl="N" original=""/>
    <value column="PO_Description" isTrl="N" original=""/>
    <value column="PO_Help" isTrl="N" original=""/>
    <value column="PO_Name" isTrl="N" original=""/>
    <value column="PO_PrintName" isTrl="N" original=""/>
  </row>
  <row id="A1E5AE7EBCBB4FC297D1DAD281F14F71" trl="Y">
    <value column="Name" isTrl="Y" original="EM_Imdlv_Product_ID">Producto</value>
    <value column="PrintName" isTrl="Y" original="EM_Imdlv_Product_ID">Producto</value>
    <value column="Description" isTrl="N" original=""/>
    <value column="Help" isTrl="N" original=""/>
    <value column="PO_Description" isTrl="N" original=""/>
    <value column="PO_Help" isTrl="N" original=""/>
    <value column="PO_Name" isTrl="N" original=""/>
    <value column="PO_PrintName" isTrl="N" original=""/>
  </row>
  <row id="A21E6CE659784278A60D8579719E2F9E" trl="N">
    <value column="Name" isTrl="N" original="Createtrx">Createtrx</value>
    <value column="PrintName" isTrl="N" original="Createtrx">Createtrx</value>
    <value column="Description" isTrl="N" original=""/>
    <value column="Help" isTrl="N" original=""/>
    <value column="PO_Description" isTrl="N" original=""/>
    <value column="PO_Help" isTrl="N" original=""/>
    <value column="PO_Name" isTrl="N" original=""/>
    <value column="PO_PrintName" isTrl="N" original=""/>
  </row>
  <row id="A3FC1F437A5C47098185B61A248298FF" trl="N">
    <value column="Name" isTrl="Y" original="Date Authorization">Fecha de Autorización</value>
    <value column="PrintName" isTrl="Y" original="Date Authorization">Fecha de Autorización</value>
    <value column="Description" isTrl="N" original=""/>
    <value column="Help" isTrl="N" original=""/>
    <value column="PO_Description" isTrl="N" original=""/>
    <value column="PO_Help" isTrl="N" original=""/>
    <value column="PO_Name" isTrl="N" original=""/>
    <value column="PO_PrintName" isTrl="N" original=""/>
  </row>
  <row id="A5244490BBFB46F08A27E2B70E2D5E56" trl="N">
    <value column="Name" isTrl="Y" original="Date Emission Withholding">Fecha emisión retención</value>
    <value column="PrintName" isTrl="Y" original="Date Emission Withholding">Fecha emisión retención</value>
    <value column="Description" isTrl="N" original=""/>
    <value column="Help" isTrl="N" original=""/>
    <value column="PO_Description" isTrl="N" original=""/>
    <value column="PO_Help" isTrl="N" original=""/>
    <value column="PO_Name" isTrl="N" original=""/>
    <value column="PO_PrintName" isTrl="N" original=""/>
  </row>
  <row id="A671989FC6244EBEA867AA78423C4EAD" trl="N">
    <value column="Name" isTrl="Y" original="Tip">Propina</value>
    <value column="PrintName" isTrl="Y" original="Tip">Propina</value>
    <value column="Description" isTrl="N" original=""/>
    <value column="Help" isTrl="N" original=""/>
    <value column="PO_Description" isTrl="N" original=""/>
    <value column="PO_Help" isTrl="N" original=""/>
    <value column="PO_Name" isTrl="N" original=""/>
    <value column="PO_PrintName" isTrl="N" original=""/>
  </row>
  <row id="A9A6569378FF4B308A4D770541E3C20F" trl="N">
    <value column="Name" isTrl="Y" original="Typetrx">Tipo de transacción</value>
    <value column="PrintName" isTrl="Y" original="Typetrx">Tipo de transacción</value>
    <value column="Description" isTrl="N" original=""/>
    <value column="Help" isTrl="N" original=""/>
    <value column="PO_Description" isTrl="N" original=""/>
    <value column="PO_Help" isTrl="N" original=""/>
    <value column="PO_Name" isTrl="N" original=""/>
    <value column="PO_PrintName" isTrl="N" original=""/>
  </row>
  <row id="A9E94AB5C2104DBEB90BE6E6A2684698" trl="N">
    <value column="Name" isTrl="N" original="Invoicetax_Income_ID">Invoicetax_Income_ID</value>
    <value column="PrintName" isTrl="N" original="Invoicetax_Income_ID">Invoicetax_Income_ID</value>
    <value column="Description" isTrl="N" original=""/>
    <value column="Help" isTrl="N" original=""/>
    <value column="PO_Description" isTrl="N" original=""/>
    <value column="PO_Help" isTrl="N" original=""/>
    <value column="PO_Name" isTrl="N" original=""/>
    <value column="PO_PrintName" isTrl="N" original=""/>
  </row>
  <row id="AB2EBA72E16648B58B9BDB9254DD5CF2" trl="N">
    <value column="Name" isTrl="N" original="Imdlv_Lines_ID">Imdlv_Lines_ID</value>
    <value column="PrintName" isTrl="N" original="Imdlv_Lines_ID">Imdlv_Lines_ID</value>
    <value column="Description" isTrl="N" original=""/>
    <value column="Help" isTrl="N" original=""/>
    <value column="PO_Description" isTrl="N" original=""/>
    <value column="PO_Help" isTrl="N" original=""/>
    <value column="PO_Name" isTrl="N" original=""/>
    <value column="PO_PrintName" isTrl="N" original=""/>
  </row>
  <row id="AFF4125BA1E249C8B64A79395821677D" trl="N">
    <value column="Name" isTrl="Y" original="Cost Center">Centro de Costos</value>
    <value column="PrintName" isTrl="Y" original="Cost Center">Centro de Costos</value>
    <value column="Description" isTrl="N" original=""/>
    <value column="Help" isTrl="N" original=""/>
    <value column="PO_Description" isTrl="N" original=""/>
    <value column="PO_Help" isTrl="N" original=""/>
    <value column="PO_Name" isTrl="N" original=""/>
    <value column="PO_PrintName" isTrl="N" original=""/>
  </row>
  <row id="B0644CDAEA7546BEA10DE8F7E107258F" trl="N">
    <value column="Name" isTrl="Y" original="Code Percentage withholding">Código de porcentaje de retención</value>
    <value column="PrintName" isTrl="Y" original="Code Percentage withholding">Código de porcentaje de retención</value>
    <value column="Description" isTrl="N" original=""/>
    <value column="Help" isTrl="N" original=""/>
    <value column="PO_Description" isTrl="N" original=""/>
    <value column="PO_Help" isTrl="N" original=""/>
    <value column="PO_Name" isTrl="N" original=""/>
    <value column="PO_PrintName" isTrl="N" original=""/>
  </row>
  <row id="B0D85A9C890340FA8A8F6CA24B04D902" trl="N">
    <value column="Name" isTrl="Y" original="Date Invoice">Fecha Factura</value>
    <value column="PrintName" isTrl="Y" original="Date Invoice">Fecha Factura</value>
    <value column="Description" isTrl="N" original=""/>
    <value column="Help" isTrl="N" original=""/>
    <value column="PO_Description" isTrl="N" original=""/>
    <value column="PO_Help" isTrl="N" original=""/>
    <value column="PO_Name" isTrl="N" original=""/>
    <value column="PO_PrintName" isTrl="N" original=""/>
  </row>
  <row id="B2257B6B75C24BF5BE400958F541DC75" trl="N">
    <value column="Name" isTrl="N" original="ICE">ICE</value>
    <value column="PrintName" isTrl="N" original="ICE">ICE</value>
    <value column="Description" isTrl="N" original=""/>
    <value column="Help" isTrl="N" original=""/>
    <value column="PO_Description" isTrl="N" original=""/>
    <value column="PO_Help" isTrl="N" original=""/>
    <value column="PO_Name" isTrl="N" original=""/>
    <value column="PO_PrintName" isTrl="N" original=""/>
  </row>
  <row id="B38065B919B94B098757B898C60D535F" trl="N">
    <value column="Name" isTrl="Y" original="Document Type Note Debit">Tipo de documento nota de crédito</value>
    <value column="PrintName" isTrl="Y" original="Document Type Credit Debit">Tipo de documento nota de crédito</value>
    <value column="Description" isTrl="N" original=""/>
    <value column="Help" isTrl="N" original=""/>
    <value column="PO_Description" isTrl="N" original=""/>
    <value column="PO_Help" isTrl="N" original=""/>
    <value column="PO_Name" isTrl="N" original=""/>
    <value column="PO_PrintName" isTrl="N" original=""/>
  </row>
  <row id="B431F9D24BCE4BD382886E43545778CA" trl="Y">
    <value column="Name" isTrl="Y" original="Type_File"> Tipo de Archivo</value>
    <value column="PrintName" isTrl="Y" original="Type_File"> Tipo de Archivo</value>
    <value column="Description" isTrl="N" original=""/>
    <value column="Help" isTrl="N" original=""/>
    <value column="PO_Description" isTrl="N" original=""/>
    <value column="PO_Help" isTrl="N" original=""/>
    <value column="PO_Name" isTrl="N" original=""/>
    <value column="PO_PrintName" isTrl="N" original=""/>
  </row>
  <row id="B5397B0E93124023AEC4ABF77F8FC391" trl="N">
    <value column="Name" isTrl="Y" original="Emision Type">Tipo de Emisión</value>
    <value column="PrintName" isTrl="Y" original="Emision Type">Tipo de Emisión</value>
    <value column="Description" isTrl="N" original=""/>
    <value column="Help" isTrl="N" original=""/>
    <value column="PO_Description" isTrl="N" original=""/>
    <value column="PO_Help" isTrl="N" original=""/>
    <value column="PO_Name" isTrl="N" original=""/>
    <value column="PO_PrintName" isTrl="N" original=""/>
  </row>
  <row id="BB2C31F8D2DF4A7F907CF4E3377478A1" trl="N">
    <value column="Name" isTrl="Y" original="Tax base">Base Imp.</value>
    <value column="PrintName" isTrl="Y" original="Tax base">Base Imp.</value>
    <value column="Description" isTrl="N" original=""/>
    <value column="Help" isTrl="N" original=""/>
    <value column="PO_Description" isTrl="N" original=""/>
    <value column="PO_Help" isTrl="N" original=""/>
    <value column="PO_Name" isTrl="N" original=""/>
    <value column="PO_PrintName" isTrl="N" original=""/>
  </row>
  <row id="BDFE383C86E24114AC0C6D5A82D1B8E2" trl="N">
    <value column="Name" isTrl="Y" original="Doctype_Without_Support_ID">Otro Fact. sin sustento</value>
    <value column="PrintName" isTrl="Y" original="Doctype_Without_Support_ID">Otro Fact. sin sustento</value>
    <value column="Description" isTrl="N" original=""/>
    <value column="Help" isTrl="N" original=""/>
    <value column="PO_Description" isTrl="N" original=""/>
    <value column="PO_Help" isTrl="N" original=""/>
    <value column="PO_Name" isTrl="N" original=""/>
    <value column="PO_PrintName" isTrl="N" original=""/>
  </row>
  <row id="BEBF708E4B5C4E5E8829FEA3B38DB5EC" trl="N">
    <value column="Name" isTrl="Y" original="Reference Invoice">Referencia de Factura</value>
    <value column="PrintName" isTrl="Y" original="Reference Invoice">Referencia de Factura</value>
    <value column="Description" isTrl="N" original=""/>
    <value column="Help" isTrl="N" original=""/>
    <value column="PO_Description" isTrl="N" original=""/>
    <value column="PO_Help" isTrl="N" original=""/>
    <value column="PO_Name" isTrl="N" original=""/>
    <value column="PO_PrintName" isTrl="N" original=""/>
  </row>
  <row id="C15A24AFFC154023B554E09A7DDDBCD2" trl="N">
    <value column="Name" isTrl="Y" original="Integrated taxes">Impuestos Integrados</value>
    <value column="PrintName" isTrl="Y" original="Integrated taxes">Impuestos Integrados</value>
    <value column="Description" isTrl="N" original=""/>
    <value column="Help" isTrl="N" original=""/>
    <value column="PO_Description" isTrl="N" original=""/>
    <value column="PO_Help" isTrl="N" original=""/>
    <value column="PO_Name" isTrl="N" original=""/>
    <value column="PO_PrintName" isTrl="N" original=""/>
  </row>
  <row id="C6F6F47EBF7041D9B4463AA708DE70AE" trl="N">
    <value column="Name" isTrl="Y" original="Purchase Invoice Default">Factura de compra por defecto</value>
    <value column="PrintName" isTrl="Y" original="Purchase Invoice Default">Factura de compra por defecto</value>
    <value column="Description" isTrl="N" original=""/>
    <value column="Help" isTrl="N" original=""/>
    <value column="PO_Description" isTrl="N" original=""/>
    <value column="PO_Help" isTrl="N" original=""/>
    <value column="PO_Name" isTrl="N" original=""/>
    <value column="PO_PrintName" isTrl="N" original=""/>
  </row>
  <row id="CB0CF02B1B784FAAAF22BE91EBBFDB0B" trl="N">
    <value column="Name" isTrl="N" original="Imdlv_Homologation_Product_ID">Imdlv_Homologation_Product_ID</value>
    <value column="PrintName" isTrl="N" original="Imdlv_Homologation_Product_ID">Imdlv_Homologation_Product_ID</value>
    <value column="Description" isTrl="N" original=""/>
    <value column="Help" isTrl="N" original=""/>
    <value column="PO_Description" isTrl="N" original=""/>
    <value column="PO_Help" isTrl="N" original=""/>
    <value column="PO_Name" isTrl="N" original=""/>
    <value column="PO_PrintName" isTrl="N" original=""/>
  </row>
  <row id="CC143515217544D09826C1000F4DF7AE" trl="N">
    <value column="Name" isTrl="N" original="Subtotal">Subtotal</value>
    <value column="PrintName" isTrl="N" original="Subtotal">Subtotal</value>
    <value column="Description" isTrl="N" original=""/>
    <value column="Help" isTrl="N" original=""/>
    <value column="PO_Description" isTrl="N" original=""/>
    <value column="PO_Help" isTrl="N" original=""/>
    <value column="PO_Name" isTrl="N" original=""/>
    <value column="PO_PrintName" isTrl="N" original=""/>
  </row>
  <row id="CCA851114DB5405294197953BD5C79B9" trl="N">
    <value column="Name" isTrl="Y" original="Type xml">Tipo XML</value>
    <value column="PrintName" isTrl="Y" original="Type xml">Tipo XML</value>
    <value column="Description" isTrl="N" original=""/>
    <value column="Help" isTrl="N" original=""/>
    <value column="PO_Description" isTrl="N" original=""/>
    <value column="PO_Help" isTrl="N" original=""/>
    <value column="PO_Name" isTrl="N" original=""/>
    <value column="PO_PrintName" isTrl="N" original=""/>
  </row>
  <row id="CEE96E1C08AF4DCBB2BE9EFD75927FEA" trl="N">
    <value column="Name" isTrl="Y" original="Key Acess">Clave de acceso</value>
    <value column="PrintName" isTrl="Y" original="Key Acess">Clave de acceso</value>
    <value column="Description" isTrl="N" original=""/>
    <value column="Help" isTrl="N" original=""/>
    <value column="PO_Description" isTrl="N" original=""/>
    <value column="PO_Help" isTrl="N" original=""/>
    <value column="PO_Name" isTrl="N" original=""/>
    <value column="PO_PrintName" isTrl="N" original=""/>
  </row>
  <row id="D091AA16CD1E4A2292CB801F1B6C1547" trl="N">
    <value column="Name" isTrl="Y" original="Status invoice">Estado de la Factura</value>
    <value column="PrintName" isTrl="Y" original="Status invoice">Estado de la Factura</value>
    <value column="Description" isTrl="N" original=""/>
    <value column="Help" isTrl="N" original=""/>
    <value column="PO_Description" isTrl="N" original=""/>
    <value column="PO_Help" isTrl="N" original=""/>
    <value column="PO_Name" isTrl="N" original=""/>
    <value column="PO_PrintName" isTrl="N" original=""/>
  </row>
  <row id="D55D130F8CBD4DF5B5ED0B4509196D89" trl="N">
    <value column="Name" isTrl="Y" original="Livelihoodt">Tipo de comprobante</value>
    <value column="PrintName" isTrl="Y" original="Livelihoodt">Tipo de comprobante</value>
    <value column="Description" isTrl="N" original=""/>
    <value column="Help" isTrl="N" original=""/>
    <value column="PO_Description" isTrl="N" original=""/>
    <value column="PO_Help" isTrl="N" original=""/>
    <value column="PO_Name" isTrl="N" original=""/>
    <value column="PO_PrintName" isTrl="N" original=""/>
  </row>
  <row id="DA0D7D0666C64A9FBA8E91DFB77EEA88" trl="N">
    <value column="Name" isTrl="Y" original="Doctype_With_Support_ID">Otro Fact. sin sustento</value>
    <value column="PrintName" isTrl="Y" original="Doctype_With_Support_ID">Otro Fact. sin sustento</value>
    <value column="Description" isTrl="N" original=""/>
    <value column="Help" isTrl="N" original=""/>
    <value column="PO_Description" isTrl="N" original=""/>
    <value column="PO_Help" isTrl="N" original=""/>
    <value column="PO_Name" isTrl="N" original=""/>
    <value column="PO_PrintName" isTrl="N" original=""/>
  </row>
  <row id="DB30CFD8FB624D3EA07A10FE159F6CF9" trl="N">
    <value column="Name" isTrl="Y" original="Date Emision">Fecha Emisión</value>
    <value column="PrintName" isTrl="Y" original="Date Emision">Fecha Emisión</value>
    <value column="Description" isTrl="N" original=""/>
    <value column="Help" isTrl="N" original=""/>
    <value column="PO_Description" isTrl="N" original=""/>
    <value column="PO_Help" isTrl="N" original=""/>
    <value column="PO_Name" isTrl="N" original=""/>
    <value column="PO_PrintName" isTrl="N" original=""/>
  </row>
  <row id="DCCF4E6F541A4D89B2997F08DC43E0E1" trl="N">
    <value column="Name" isTrl="N" original="Base Renta">Base Renta</value>
    <value column="PrintName" isTrl="N" original="Base Renta">Base Renta</value>
    <value column="Description" isTrl="N" original=""/>
    <value column="Help" isTrl="N" original=""/>
    <value column="PO_Description" isTrl="N" original=""/>
    <value column="PO_Help" isTrl="N" original=""/>
    <value column="PO_Name" isTrl="N" original=""/>
    <value column="PO_PrintName" isTrl="N" original=""/>
  </row>
  <row id="E12970C4F66F45DA93EDDD0CBC92E4B8" trl="N">
    <value column="Name" isTrl="Y" original="Total Invoice">Total Factura</value>
    <value column="PrintName" isTrl="Y" original="Total Invoice">Total Factura</value>
    <value column="Description" isTrl="N" original=""/>
    <value column="Help" isTrl="N" original=""/>
    <value column="PO_Description" isTrl="N" original=""/>
    <value column="PO_Help" isTrl="N" original=""/>
    <value column="PO_Name" isTrl="N" original=""/>
    <value column="PO_PrintName" isTrl="N" original=""/>
  </row>
  <row id="E217E2E68CB94C37B704DD1686DDABF8" trl="Y">
    <value column="Name" isTrl="Y" original="Product_File">Producto Archivo</value>
    <value column="PrintName" isTrl="Y" original="Product_File">Producto Archivo</value>
    <value column="Description" isTrl="N" original=""/>
    <value column="Help" isTrl="N" original=""/>
    <value column="PO_Description" isTrl="N" original=""/>
    <value column="PO_Help" isTrl="N" original=""/>
    <value column="PO_Name" isTrl="N" original=""/>
    <value column="PO_PrintName" isTrl="N" original=""/>
  </row>
  <row id="E35AE4BFD438472893595ABCC9642A7A" trl="N">
    <value column="Name" isTrl="Y" original="Total withholding VAT">Total retención IVA</value>
    <value column="PrintName" isTrl="Y" original="Total withholding VAT">Total retención IVA</value>
    <value column="Description" isTrl="N" original=""/>
    <value column="Help" isTrl="N" original=""/>
    <value column="PO_Description" isTrl="N" original=""/>
    <value column="PO_Help" isTrl="N" original=""/>
    <value column="PO_Name" isTrl="N" original=""/>
    <value column="PO_PrintName" isTrl="N" original=""/>
  </row>
  <row id="E470AC2A1D4B4C299B61F985DDEEEB5F" trl="N">
    <value column="Name" isTrl="N" original="Qty">Qty</value>
    <value column="PrintName" isTrl="N" original="Qty">Qty</value>
    <value column="Description" isTrl="N" original=""/>
    <value column="Help" isTrl="N" original=""/>
    <value column="PO_Description" isTrl="N" original=""/>
    <value column="PO_Help" isTrl="N" original=""/>
    <value column="PO_Name" isTrl="N" original=""/>
    <value column="PO_PrintName" isTrl="N" original=""/>
  </row>
  <row id="E52BCC4128664133A8ED2FCF4C19D693" trl="N">
    <value column="Name" isTrl="Y" original="Document Type credit note">Tipo de documento nota de crédito</value>
    <value column="PrintName" isTrl="Y" original="Document Type credit note">Tipo de documento nota de crédito</value>
    <value column="Description" isTrl="N" original=""/>
    <value column="Help" isTrl="N" original=""/>
    <value column="PO_Description" isTrl="N" original=""/>
    <value column="PO_Help" isTrl="N" original=""/>
    <value column="PO_Name" isTrl="N" original=""/>
    <value column="PO_PrintName" isTrl="N" original=""/>
  </row>
  <row id="ED2DA7F05CEA4B65A7687E9B1AB1DCE9" trl="N">
    <value column="Name" isTrl="Y" original="Partner">Tercero por Defecto</value>
    <value column="PrintName" isTrl="Y" original="Partner">Tercero por Defecto</value>
    <value column="Description" isTrl="N" original=""/>
    <value column="Help" isTrl="N" original=""/>
    <value column="PO_Description" isTrl="N" original=""/>
    <value column="PO_Help" isTrl="N" original=""/>
    <value column="PO_Name" isTrl="N" original=""/>
    <value column="PO_PrintName" isTrl="N" original=""/>
  </row>
  <row id="F128191BF91649D78FD3A2C6B6FF1CDA" trl="N">
    <value column="Name" isTrl="Y" original="Support Document">Documento Sustento</value>
    <value column="PrintName" isTrl="Y" original="Support Document">Documento Sustento</value>
    <value column="Description" isTrl="N" original=""/>
    <value column="Help" isTrl="N" original=""/>
    <value column="PO_Description" isTrl="N" original=""/>
    <value column="PO_Help" isTrl="N" original=""/>
    <value column="PO_Name" isTrl="N" original=""/>
    <value column="PO_PrintName" isTrl="N" original=""/>
  </row>
  <row id="F178952C47224647A5EB83EFC196AAEA" trl="N">
    <value column="Name" isTrl="Y" original="Doctype Purchase">Tipo de documento de compra</value>
    <value column="PrintName" isTrl="Y" original="Doctype Purchase">Tipo de documento de compra</value>
    <value column="Description" isTrl="N" original=""/>
    <value column="Help" isTrl="N" original=""/>
    <value column="PO_Description" isTrl="N" original=""/>
    <value column="PO_Help" isTrl="N" original=""/>
    <value column="PO_Name" isTrl="N" original=""/>
    <value column="PO_PrintName" isTrl="N" original=""/>
  </row>
  <row id="F404D96629D745E3B5371B4743A1250C" trl="N">
    <value column="Name" isTrl="N" original="Bpartner_ID">Bpartner_ID</value>
    <value column="PrintName" isTrl="N" original="Bpartner_ID">Bpartner_ID</value>
    <value column="Description" isTrl="N" original=""/>
    <value column="Help" isTrl="N" original=""/>
    <value column="PO_Description" isTrl="N" original=""/>
    <value column="PO_Help" isTrl="N" original=""/>
    <value column="PO_Name" isTrl="N" original=""/>
    <value column="PO_PrintName" isTrl="N" original=""/>
  </row>
  <row id="F46AA5AB983246ADAD02F925834EF9F9" trl="N">
    <value column="Name" isTrl="N" original="Refundedinvoice_Ref_ID">Refundedinvoice_Ref_ID</value>
    <value column="PrintName" isTrl="N" original="Refundedinvoice_Ref_ID">Refundedinvoice_Ref_ID</value>
    <value column="Description" isTrl="N" original=""/>
    <value column="Help" isTrl="N" original=""/>
    <value column="PO_Description" isTrl="N" original=""/>
    <value column="PO_Help" isTrl="N" original=""/>
    <value column="PO_Name" isTrl="N" original=""/>
    <value column="PO_PrintName" isTrl="N" original=""/>
  </row>
  <row id="F6D359896DDE4BF4BDFCDA021BA83704" trl="N">
    <value column="Name" isTrl="N" original="Bpartner_Ref">Bpartner_Ref</value>
    <value column="PrintName" isTrl="N" original="Bpartner_Ref">Bpartner_Ref</value>
    <value column="Description" isTrl="N" original=""/>
    <value column="Help" isTrl="N" original=""/>
    <value column="PO_Description" isTrl="N" original=""/>
    <value column="PO_Help" isTrl="N" original=""/>
    <value column="PO_Name" isTrl="N" original=""/>
    <value column="PO_PrintName" isTrl="N" original=""/>
  </row>
  <row id="F6F13B090A544B7F9133C8E7B8B7D1F5" trl="N">
    <value column="Name" isTrl="Y" original="Date Import">Fecha de importación</value>
    <value column="PrintName" isTrl="Y" original="Date Import">Fecha de importación</value>
    <value column="Description" isTrl="N" original=""/>
    <value column="Help" isTrl="N" original=""/>
    <value column="PO_Description" isTrl="N" original=""/>
    <value column="PO_Help" isTrl="N" original=""/>
    <value column="PO_Name" isTrl="N" original=""/>
    <value column="PO_PrintName" isTrl="N" original=""/>
  </row>
  <row id="F7AB974690D74FC1A48DD6C2D523C7DA" trl="N">
    <value column="Name" isTrl="Y" original="Base VAT">Base IVA</value>
    <value column="PrintName" isTrl="Y" original="Base VAT">Base IVA</value>
    <value column="Description" isTrl="N" original=""/>
    <value column="Help" isTrl="N" original=""/>
    <value column="PO_Description" isTrl="N" original=""/>
    <value column="PO_Help" isTrl="N" original=""/>
    <value column="PO_Name" isTrl="N" original=""/>
    <value column="PO_PrintName" isTrl="N" original=""/>
  </row>
  <row id="F913A1AC5D2D422F9C37C3DAC3D7A091" trl="N">
    <value column="Name" isTrl="N" original="Createlines">Createlines</value>
    <value column="PrintName" isTrl="N" original="Createlines">Createlines</value>
    <value column="Description" isTrl="N" original=""/>
    <value column="Help" isTrl="N" original=""/>
    <value column="PO_Description" isTrl="N" original=""/>
    <value column="PO_Help" isTrl="N" original=""/>
    <value column="PO_Name" isTrl="N" original=""/>
    <value column="PO_PrintName" isTrl="N" original=""/>
  </row>
  <row id="F9FCDB8613C9494D87A75C1F90146E7A" trl="N">
    <value column="Name" isTrl="N" original="TAX_Ref">TAX_Ref</value>
    <value column="PrintName" isTrl="N" original="TAX_Ref">TAX_Ref</value>
    <value column="Description" isTrl="N" original="The percentage of money requested by the government for this specified product or transaction.">The percentage of money requested by the government for this specified product or transaction.</value>
    <value column="Help" isTrl="N" original="The Tax indicates the type of tax for this document line.">The Tax indicates the type of tax for this document line.</value>
    <value column="PO_Description" isTrl="N" original=""/>
    <value column="PO_Help" isTrl="N" original=""/>
    <value column="PO_Name" isTrl="N" original=""/>
    <value column="PO_PrintName" isTrl="N" original=""/>
  </row>
  <row id="FCC63AD3CD9742F29A08060CE4F3A118" trl="N">
    <value column="Name" isTrl="Y" original="Withh. VAT">Retención IVA</value>
    <value column="PrintName" isTrl="Y" original="Withh. VAT">Retención IVA</value>
    <value column="Description" isTrl="N" original=""/>
    <value column="Help" isTrl="N" original=""/>
    <value column="PO_Description" isTrl="N" original=""/>
    <value column="PO_Help" isTrl="N" original=""/>
    <value column="PO_Name" isTrl="N" original=""/>
    <value column="PO_PrintName" isTrl="N" original=""/>
  </row>
  <row id="FDEE30BEF17E409C82C29264EA1C1C0A" trl="N">
    <value column="Name" isTrl="Y" original="Document Type Order">Tipo de documento pedido</value>
    <value column="PrintName" isTrl="N" original="Document Type Order">Document Type Order</value>
    <value column="Description" isTrl="N" original=""/>
    <value column="Help" isTrl="N" original=""/>
    <value column="PO_Description" isTrl="N" original=""/>
    <value column="PO_Help" isTrl="N" original=""/>
    <value column="PO_Name" isTrl="N" original=""/>
    <value column="PO_PrintName" isTrl="N" original=""/>
  </row>
</compiereTrl>
